big_text/__init__.py
big_text/__main__.py
big_text/data.py
big_text-0.2.1.dist-info/METADATA
big_text-0.2.1.dist-info/WHEEL
big_text-0.2.1.dist-info/entry_points.txt
big_text-0.2.1.dist-info/licenses/LICENSE
big_text-0.2.1.dist-info/RECORD
