Metadata-Version: 2.4
Name: big_text
Version: 0.2.1
Summary: Generate ascii art from text input.
Author-email: Geoffrey Lentner <glentner@purdue.edu>
License-Expression: MIT
License-File: LICENSE
Keywords: command-line,utility
Classifier: Development Status :: 5 - Production/Stable
Classifier: License :: OSI Approved :: MIT License
Classifier: Programming Language :: Python :: 3.9
Classifier: Programming Language :: Python :: 3.10
Classifier: Programming Language :: Python :: 3.11
Classifier: Programming Language :: Python :: 3.12
Classifier: Programming Language :: Python :: 3.13
Classifier: Programming Language :: Python :: 3.14
Requires-Python: >=3.9
Requires-Dist: cmdkit>=2.7.7
